LICENSE
README.md
setup.cfg
setup.py
crypto_pay_tools/__init__.py
crypto_pay_tools/crypto_payment.py
crypto_pay_tools/exceptions.py
crypto_pay_tools.egg-info/PKG-INFO
crypto_pay_tools.egg-info/SOURCES.txt
crypto_pay_tools.egg-info/dependency_links.txt
crypto_pay_tools.egg-info/top_level.txt