Metadata-Version: 2.1
Name: crypto-pay-tools
Version: 0.1.0
Summary: A tool for quickly connecting a cryptocurrency payment system in Telegram.
Author-email: vlad.eat@yandex.ru
License: UNKNOWN
Platform: UNKNOWN
License-File: LICENSE
